[
    {
        "band": "Watsky",
        "album": "x Infinity",
        "song": "Pink Lemonade"
    },
    {
        "band": "Logic",
        "album": "The Incredible True Story",
        "song": "Lord Willin'"
    },
    {
        "band": "Coldplay",
        "album": "Parachutes",
        "song": "Yellow"
    },
    {
        "band": "Andy Grammer",
        "album": "Magazines or Novels",
        "song": "Honey, I'm Good."
    },
    {
        "album": "Test",
        "band": "test",
        "song": "test2"
    }
]